pyOpenSubdiv/__init__.py
pyOpenSubdiv/pysubdivision.py
pyOpenSubdiv/test_topology.py
pyOpenSubdiv/clib/__init__.py
pyOpenSubdiv/clib/ctypes_OpenSubdiv.dll
pyOpenSubdiv/clib/ctypes_OpenSubdiv.so
pyOpenSubdiv/clib/load_library.py
pyOpenSubdiv-0.0.3.dist-info/METADATA
pyOpenSubdiv-0.0.3.dist-info/WHEEL
pyOpenSubdiv-0.0.3.dist-info/top_level.txt
pyOpenSubdiv-0.0.3.dist-info/RECORD
